[
  {
    "site": "https://www.linkedin.com/in/yago-emanuel-brito-de-moura-417385275/recent-activity/all/",
    "texto": "",
    "href": "/"
  },
  {
    "site": "https://www.linkedin.com/in/yago-emanuel-brito-de-moura-417385275/recent-activity/all/",
    "texto": "Forgot password?",
    "href": "/checkpoint/rp/request-password-reset?session_redirect=https%3A%2F%2Fwww%2Elinkedin%2Ecom%2Fin%2Fyago-emanuel-brito-de-moura-417385275%2Frecent-activity%2Fall%2F"
  },
  {
    "site": "https://www.linkedin.com/in/yago-emanuel-brito-de-moura-417385275/recent-activity/all/",
    "texto": "Join now",
    "href": "/signup/cold-join?session_redirect=https%3A%2F%2Fwww.linkedin.com%2Fin%2Fyago-emanuel-brito-de-moura-417385275%2Frecent-activity%2Fall%2F"
  },
  {
    "site": "https://www.linkedin.com/in/yago-emanuel-brito-de-moura-417385275/recent-activity/all/",
    "texto": "User Agreement",
    "href": "/legal/user-agreement"
  },
  {
    "site": "https://www.linkedin.com/in/yago-emanuel-brito-de-moura-417385275/recent-activity/all/",
    "texto": "Privacy Policy",
    "href": "/legal/privacy-policy"
  },
  {
    "site": "https://www.linkedin.com/in/yago-emanuel-brito-de-moura-417385275/recent-activity/all/",
    "texto": "Cookie Policy",
    "href": "/legal/cookie-policy"
  },
  {
    "site": "https://www.linkedin.com/in/yago-emanuel-brito-de-moura-417385275/recent-activity/all/",
    "texto": "User Agreement",
    "href": "/legal/user-agreement?trk=d_checkpoint_lg_consumerLogin_ft_user_agreement"
  },
  {
    "site": "https://www.linkedin.com/in/yago-emanuel-brito-de-moura-417385275/recent-activity/all/",
    "texto": "Privacy Policy",
    "href": "/legal/privacy-policy?trk=d_checkpoint_lg_consumerLogin_ft_privacy_policy"
  },
  {
    "site": "https://www.linkedin.com/in/yago-emanuel-brito-de-moura-417385275/recent-activity/all/",
    "texto": "Community Guidelines",
    "href": "/help/linkedin/answer/34593?lang=en&trk=d_checkpoint_lg_consumerLogin_ft_community_guidelines"
  },
  {
    "site": "https://www.linkedin.com/in/yago-emanuel-brito-de-moura-417385275/recent-activity/all/",
    "texto": "Cookie Policy",
    "href": "/legal/cookie-policy?trk=d_checkpoint_lg_consumerLogin_ft_cookie_policy"
  },
  {
    "site": "https://www.linkedin.com/in/yago-emanuel-brito-de-moura-417385275/recent-activity/all/",
    "texto": "Copyright Policy",
    "href": "/legal/copyright-policy?trk=d_checkpoint_lg_consumerLogin_ft_copyright_policy"
  },
  {
    "site": "https://www.linkedin.com/in/yago-emanuel-brito-de-moura-417385275/recent-activity/all/",
    "texto": "Send Feedback",
    "href": "/help/linkedin?trk=d_checkpoint_lg_consumerLogin_ft_send_feedback&lang=en"
  },
  {
    "site": "https://github.com/Ybrittoom?tab=repositories",
    "texto": "Skip to content",
    "href": "#start-of-content"
  },
  {
    "site": "https://github.com/Ybrittoom?tab=repositories",
    "texto": "",
    "href": "/"
  },
  {
    "site": "https://github.com/Ybrittoom?tab=repositories",
    "texto": "Sign in",
    "href": "/login?return_to=https%3A%2F%2Fgithub.com%2FYbrittoom%3Ftab%3Drepositories"
  },
  {
    "site": "https://github.com/Ybrittoom?tab=repositories",
    "texto": "GitHub Copilot\n        Write better code with AI",
    "href": "https://github.com/features/copilot"
  },
  {
    "site": "https://github.com/Ybrittoom?tab=repositories",
    "texto": "GitHub Advanced Security\n        Find and fix vulnerabilities",
    "href": "https://github.com/security/advanced-security"
  },
  {
    "site": "https://github.com/Ybrittoom?tab=repositories",
    "texto": "Actions\n        Automate any workflow",
    "href": "https://github.com/features/actions"
  },
  {
    "site": "https://github.com/Ybrittoom?tab=repositories",
    "texto": "Codespaces\n        Instant dev environments",
    "href": "https://github.com/features/codespaces"
  },
  {
    "site": "https://github.com/Ybrittoom?tab=repositories",
    "texto": "Issues\n        Plan and track work",
    "href": "https://github.com/features/issues"
  },
  {
    "site": "https://github.com/Ybrittoom?tab=repositories",
    "texto": "Code Review\n        Manage code changes",
    "href": "https://github.com/features/code-review"
  },
  {
    "site": "https://github.com/Ybrittoom?tab=repositories",
    "texto": "Discussions\n        Collaborate outside of code",
    "href": "https://github.com/features/discussions"
  },
  {
    "site": "https://github.com/Ybrittoom?tab=repositories",
    "texto": "Code Search\n        Find more, search less",
    "href": "https://github.com/features/code-search"
  },
  {
    "site": "https://github.com/Ybrittoom?tab=repositories",
    "texto": "Why GitHub",
    "href": "https://github.com/why-github"
  },
  {
    "site": "https://github.com/Ybrittoom?tab=repositories",
    "texto": "All features",
    "href": "https://github.com/features"
  },
  {
    "site": "https://github.com/Ybrittoom?tab=repositories",
    "texto": "Documentation",
    "href": "https://docs.github.com"
  },
  {
    "site": "https://github.com/Ybrittoom?tab=repositories",
    "texto": "GitHub Skills",
    "href": "https://skills.github.com"
  },
  {
    "site": "https://github.com/Ybrittoom?tab=repositories",
    "texto": "Blog",
    "href": "https://github.blog"
  },
  {
    "site": "https://github.com/Ybrittoom?tab=repositories",
    "texto": "Enterprises",
    "href": "https://github.com/enterprise"
  },
  {
    "site": "https://github.com/Ybrittoom?tab=repositories",
    "texto": "Small and medium teams",
    "href": "https://github.com/team"
  },
  {
    "site": "https://github.com/Ybrittoom?tab=repositories",
    "texto": "Startups",
    "href": "https://github.com/enterprise/startups"
  },
  {
    "site": "https://github.com/Ybrittoom?tab=repositories",
    "texto": "Nonprofits",
    "href": "/solutions/industry/nonprofits"
  },
  {
    "site": "https://github.com/Ybrittoom?tab=repositories",
    "texto": "DevSecOps",
    "href": "/solutions/use-case/devsecops"
  },
  {
    "site": "https://github.com/Ybrittoom?tab=repositories",
    "texto": "DevOps",
    "href": "/solutions/use-case/devops"
  },
  {
    "site": "https://github.com/Ybrittoom?tab=repositories",
    "texto": "CI/CD",
    "href": "/solutions/use-case/ci-cd"
  },
  {
    "site": "https://github.com/Ybrittoom?tab=repositories",
    "texto": "View all use cases",
    "href": "/solutions/use-case"
  },
  {
    "site": "https://github.com/Ybrittoom?tab=repositories",
    "texto": "Healthcare",
    "href": "/solutions/industry/healthcare"
  },
  {
    "site": "https://github.com/Ybrittoom?tab=repositories",
    "texto": "Financial services",
    "href": "/solutions/industry/financial-services"
  },
  {
    "site": "https://github.com/Ybrittoom?tab=repositories",
    "texto": "Manufacturing",
    "href": "/solutions/industry/manufacturing"
  },
  {
    "site": "https://github.com/Ybrittoom?tab=repositories",
    "texto": "Government",
    "href": "/solutions/industry/government"
  },
  {
    "site": "https://github.com/Ybrittoom?tab=repositories",
    "texto": "View all industries",
    "href": "/solutions/industry"
  },
  {
    "site": "https://github.com/Ybrittoom?tab=repositories",
    "texto": "View all solutions",
    "href": "/solutions"
  },
  {
    "site": "https://github.com/Ybrittoom?tab=repositories",
    "texto": "AI",
    "href": "/resources/articles/ai"
  },
  {
    "site": "https://github.com/Ybrittoom?tab=repositories",
    "texto": "DevOps",
    "href": "/resources/articles/devops"
  },
  {
    "site": "https://github.com/Ybrittoom?tab=repositories",
    "texto": "Security",
    "href": "/resources/articles/security"
  },
  {
    "site": "https://github.com/Ybrittoom?tab=repositories",
    "texto": "Software Development",
    "href": "/resources/articles/software-development"
  },
  {
    "site": "https://github.com/Ybrittoom?tab=repositories",
    "texto": "View all",
    "href": "/resources/articles"
  },
  {
    "site": "https://github.com/Ybrittoom?tab=repositories",
    "texto": "Learning Pathways",
    "href": "https://resources.github.com/learn/pathways"
  },
  {
    "site": "https://github.com/Ybrittoom?tab=repositories",
    "texto": "Events & Webinars",
    "href": "https://resources.github.com"
  },
  {
    "site": "https://github.com/Ybrittoom?tab=repositories",
    "texto": "Ebooks & Whitepapers",
    "href": "https://github.com/resources/whitepapers"
  },
  {
    "site": "https://github.com/Ybrittoom?tab=repositories",
    "texto": "Customer Stories",
    "href": "https://github.com/customer-stories"
  },
  {
    "site": "https://github.com/Ybrittoom?tab=repositories",
    "texto": "Partners",
    "href": "https://partner.github.com"
  },
  {
    "site": "https://github.com/Ybrittoom?tab=repositories",
    "texto": "Executive Insights",
    "href": "https://github.com/solutions/executive-insights"
  },
  {
    "site": "https://github.com/Ybrittoom?tab=repositories",
    "texto": "GitHub Sponsors\n        Fund open source developers",
    "href": "/sponsors"
  },
  {
    "site": "https://github.com/Ybrittoom?tab=repositories",
    "texto": "The ReadME Project\n        GitHub community articles",
    "href": "https://github.com/readme"
  },
  {
    "site": "https://github.com/Ybrittoom?tab=repositories",
    "texto": "Topics",
    "href": "https://github.com/topics"
  },
  {
    "site": "https://github.com/Ybrittoom?tab=repositories",
    "texto": "Trending",
    "href": "https://github.com/trending"
  },
  {
    "site": "https://github.com/Ybrittoom?tab=repositories",
    "texto": "Collections",
    "href": "https://github.com/collections"
  },
  {
    "site": "https://github.com/Ybrittoom?tab=repositories",
    "texto": "Enterprise platform\n        AI-powered developer platform",
    "href": "/enterprise"
  },
  {
    "site": "https://github.com/Ybrittoom?tab=repositories",
    "texto": "GitHub Advanced Security\n        Enterprise-grade security features",
    "href": "https://github.com/security/advanced-security"
  },
  {
    "site": "https://github.com/Ybrittoom?tab=repositories",
    "texto": "Copilot for business\n        Enterprise-grade AI features",
    "href": "/features/copilot/copilot-business"
  },
  {
    "site": "https://github.com/Ybrittoom?tab=repositories",
    "texto": "Premium Support\n        Enterprise-grade 24/7 support",
    "href": "/premium-support"
  },
  {
    "site": "https://github.com/Ybrittoom?tab=repositories",
    "texto": "Pricing",
    "href": "https://github.com/pricing"
  },
  {
    "site": "https://github.com/Ybrittoom?tab=repositories",
    "texto": "Search syntax tips",
    "href": "https://docs.github.com/search-github/github-code-search/understanding-github-code-search-syntax"
  },
  {
    "site": "https://github.com/Ybrittoom?tab=repositories",
    "texto": "documentation",
    "href": "https://docs.github.com/search-github/github-code-search/understanding-github-code-search-syntax"
  },
  {
    "site": "https://github.com/Ybrittoom?tab=repositories",
    "texto": "Sign in",
    "href": "/login?return_to=https%3A%2F%2Fgithub.com%2FYbrittoom%3Ftab%3Drepositories"
  },
  {
    "site": "https://github.com/Ybrittoom?tab=repositories",
    "texto": "Sign up",
    "href": "/signup?ref_cta=Sign+up&ref_loc=header+logged+out&ref_page=%2FYbrittoom&source=header"
  },
  {
    "site": "https://github.com/Ybrittoom?tab=repositories",
    "texto": "Follow",
    "href": "/login?return_to=https%3A%2F%2Fgithub.com%2FYbrittoom%3Ftab%3Drepositories"
  },
  {
    "site": "https://github.com/Ybrittoom?tab=repositories",
    "texto": "Overview",
    "href": "/Ybrittoom"
  },
  {
    "site": "https://github.com/Ybrittoom?tab=repositories",
    "texto": "Repositories\n    50",
    "href": "/Ybrittoom?tab=repositories"
  },
  {
    "site": "https://github.com/Ybrittoom?tab=repositories",
    "texto": "Projects\n    0",
    "href": "/Ybrittoom?tab=projects"
  },
  {
    "site": "https://github.com/Ybrittoom?tab=repositories",
    "texto": "Packages\n      0",
    "href": "/Ybrittoom?tab=packages"
  },
  {
    "site": "https://github.com/Ybrittoom?tab=repositories",
    "texto": "Stars\n    7",
    "href": "/Ybrittoom?tab=stars"
  },
  {
    "site": "https://github.com/Ybrittoom?tab=repositories",
    "texto": "Overview",
    "href": "/Ybrittoom"
  },
  {
    "site": "https://github.com/Ybrittoom?tab=repositories",
    "texto": "Repositories",
    "href": "/Ybrittoom?tab=repositories"
  },
  {
    "site": "https://github.com/Ybrittoom?tab=repositories",
    "texto": "Projects",
    "href": "/Ybrittoom?tab=projects"
  },
  {
    "site": "https://github.com/Ybrittoom?tab=repositories",
    "texto": "Packages",
    "href": "/Ybrittoom?tab=packages"
  },
  {
    "site": "https://github.com/Ybrittoom?tab=repositories",
    "texto": "Stars",
    "href": "/Ybrittoom?tab=stars"
  },
  {
    "site": "https://github.com/Ybrittoom?tab=repositories",
    "texto": "Follow",
    "href": "/login?return_to=https%3A%2F%2Fgithub.com%2FYbrittoom%3Ftab%3Drepositories"
  },
  {
    "site": "https://github.com/Ybrittoom?tab=repositories",
    "texto": "",
    "href": "https://avatars.githubusercontent.com/u/150179517?v=4"
  },
  {
    "site": "https://github.com/Ybrittoom?tab=repositories",
    "texto": "Follow",
    "href": "/login?return_to=https%3A%2F%2Fgithub.com%2FYbrittoom%3Ftab%3Drepositories"
  },
  {
    "site": "https://github.com/Ybrittoom?tab=repositories",
    "texto": "3\n          followers",
    "href": "https://github.com/Ybrittoom?tab=followers"
  },
  {
    "site": "https://github.com/Ybrittoom?tab=repositories",
    "texto": "8\n          following",
    "href": "https://github.com/Ybrittoom?tab=following"
  },
  {
    "site": "https://github.com/Ybrittoom?tab=repositories",
    "texto": "blocking users",
    "href": "https://docs.github.com/articles/blocking-a-user-from-your-personal-account"
  },
  {
    "site": "https://github.com/Ybrittoom?tab=repositories",
    "texto": "reporting abuse",
    "href": "https://docs.github.com/articles/reporting-abuse-or-spam"
  },
  {
    "site": "https://github.com/Ybrittoom?tab=repositories",
    "texto": "Report abuse",
    "href": "/contact/report-abuse?report=Ybrittoom+%28user%29"
  },
  {
    "site": "https://github.com/Ybrittoom?tab=repositories",
    "texto": "Overview",
    "href": "/Ybrittoom"
  },
  {
    "site": "https://github.com/Ybrittoom?tab=repositories",
    "texto": "Repositories\n    50",
    "href": "/Ybrittoom?tab=repositories"
  },
  {
    "site": "https://github.com/Ybrittoom?tab=repositories",
    "texto": "Projects\n    0",
    "href": "/Ybrittoom?tab=projects"
  },
  {
    "site": "https://github.com/Ybrittoom?tab=repositories",
    "texto": "Packages\n      0",
    "href": "/Ybrittoom?tab=packages"
  },
  {
    "site": "https://github.com/Ybrittoom?tab=repositories",
    "texto": "Stars\n    7",
    "href": "/Ybrittoom?tab=stars"
  },
  {
    "site": "https://github.com/Ybrittoom?tab=repositories",
    "texto": "Overview",
    "href": "/Ybrittoom"
  },
  {
    "site": "https://github.com/Ybrittoom?tab=repositories",
    "texto": "Repositories",
    "href": "/Ybrittoom?tab=repositories"
  },
  {
    "site": "https://github.com/Ybrittoom?tab=repositories",
    "texto": "Projects",
    "href": "/Ybrittoom?tab=projects"
  },
  {
    "site": "https://github.com/Ybrittoom?tab=repositories",
    "texto": "Packages",
    "href": "/Ybrittoom?tab=packages"
  },
  {
    "site": "https://github.com/Ybrittoom?tab=repositories",
    "texto": "Stars",
    "href": "/Ybrittoom?tab=stars"
  },
  {
    "site": "https://github.com/Ybrittoom?tab=repositories",
    "texto": "crawler_example",
    "href": "/Ybrittoom/crawler_example"
  },
  {
    "site": "https://github.com/Ybrittoom?tab=repositories",
    "texto": "cadastro_condominio",
    "href": "/Ybrittoom/cadastro_condominio"
  },
  {
    "site": "https://github.com/Ybrittoom?tab=repositories",
    "texto": "nextjs_teste_manual",
    "href": "/Ybrittoom/nextjs_teste_manual"
  },
  {
    "site": "https://github.com/Ybrittoom?tab=repositories",
    "texto": "system_monitor",
    "href": "/Ybrittoom/system_monitor"
  },
  {
    "site": "https://github.com/Ybrittoom?tab=repositories",
    "texto": "sistemas_de_notas",
    "href": "/Ybrittoom/sistemas_de_notas"
  },
  {
    "site": "https://github.com/Ybrittoom?tab=repositories",
    "texto": "25_APIs",
    "href": "/Ybrittoom/25_APIs"
  },
  {
    "site": "https://github.com/Ybrittoom?tab=repositories",
    "texto": "gym_registration",
    "href": "/Ybrittoom/gym_registration"
  },
  {
    "site": "https://github.com/Ybrittoom?tab=repositories",
    "texto": "gerenciamento_de_livros",
    "href": "/Ybrittoom/gerenciamento_de_livros"
  },
  {
    "site": "https://github.com/Ybrittoom?tab=repositories",
    "texto": "extra-ao_de_logs",
    "href": "/Ybrittoom/extra-ao_de_logs"
  },
  {
    "site": "https://github.com/Ybrittoom?tab=repositories",
    "texto": "previsao_do_tempo_terminal",
    "href": "/Ybrittoom/previsao_do_tempo_terminal"
  },
  {
    "site": "https://github.com/Ybrittoom?tab=repositories",
    "texto": "conversor_de_temperatura",
    "href": "/Ybrittoom/conversor_de_temperatura"
  },
  {
    "site": "https://github.com/Ybrittoom?tab=repositories",
    "texto": "validador_CPFs_html_css",
    "href": "/Ybrittoom/validador_CPFs_html_css"
  },
  {
    "site": "https://github.com/Ybrittoom?tab=repositories",
    "texto": "1",
    "href": "/Ybrittoom/validador_CPFs_html_css/forks"
  },
  {
    "site": "https://github.com/Ybrittoom?tab=repositories",
    "texto": "validador_de_CPFs",
    "href": "/Ybrittoom/validador_de_CPFs"
  },
  {
    "site": "https://github.com/Ybrittoom?tab=repositories",
    "texto": "nails_site",
    "href": "/Ybrittoom/nails_site"
  },
  {
    "site": "https://github.com/Ybrittoom?tab=repositories",
    "texto": "escola_de_musical_nestjs",
    "href": "/Ybrittoom/escola_de_musical_nestjs"
  },
  {
    "site": "https://github.com/Ybrittoom?tab=repositories",
    "texto": "Ybrittoom",
    "href": "/Ybrittoom/Ybrittoom"
  },
  {
    "site": "https://github.com/Ybrittoom?tab=repositories",
    "texto": "api-estudos-yago-",
    "href": "/Ybrittoom/api-estudos-yago-"
  },
  {
    "site": "https://github.com/Ybrittoom?tab=repositories",
    "texto": "simbaravel23/api-estudos",
    "href": "/simbaravel23/api-estudos"
  },
  {
    "site": "https://github.com/Ybrittoom?tab=repositories",
    "texto": "teste",
    "href": "/Ybrittoom/teste"
  },
  {
    "site": "https://github.com/Ybrittoom?tab=repositories",
    "texto": "mysql_escola_de_musica",
    "href": "/Ybrittoom/mysql_escola_de_musica"
  },
  {
    "site": "https://github.com/Ybrittoom?tab=repositories",
    "texto": "1",
    "href": "/Ybrittoom/mysql_escola_de_musica/forks"
  },
  {
    "site": "https://github.com/Ybrittoom?tab=repositories",
    "texto": "create_database_mysql",
    "href": "/Ybrittoom/create_database_mysql"
  },
  {
    "site": "https://github.com/Ybrittoom?tab=repositories",
    "texto": "gem_mysql",
    "href": "/Ybrittoom/gem_mysql"
  },
  {
    "site": "https://github.com/Ybrittoom?tab=repositories",
    "texto": "gem_db_json",
    "href": "/Ybrittoom/gem_db_json"
  },
  {
    "site": "https://github.com/Ybrittoom?tab=repositories",
    "texto": "GEM-Grupo-De-Estudo-Musical",
    "href": "/Ybrittoom/GEM-Grupo-De-Estudo-Musical"
  },
  {
    "site": "https://github.com/Ybrittoom?tab=repositories",
    "texto": "regex_Project",
    "href": "/Ybrittoom/regex_Project"
  },
  {
    "site": "https://github.com/Ybrittoom?tab=repositories",
    "texto": "owl_dev",
    "href": "/Ybrittoom/owl_dev"
  },
  {
    "site": "https://github.com/Ybrittoom?tab=repositories",
    "texto": "15_list",
    "href": "/Ybrittoom/15_list"
  },
  {
    "site": "https://github.com/Ybrittoom?tab=repositories",
    "texto": "APIs_mocks",
    "href": "/Ybrittoom/APIs_mocks"
  },
  {
    "site": "https://github.com/Ybrittoom?tab=repositories",
    "texto": "APIs_routes3",
    "href": "/Ybrittoom/APIs_routes3"
  },
  {
    "site": "https://github.com/Ybrittoom?tab=repositories",
    "texto": "APIs_routes2",
    "href": "/Ybrittoom/APIs_routes2"
  },
  {
    "site": "https://github.com/Ybrittoom?tab=repositories",
    "texto": "routes_APIs",
    "href": "/Ybrittoom/routes_APIs"
  },
  {
    "site": "https://github.com/Ybrittoom?tab=repositories",
    "texto": "Next",
    "href": "/Ybrittoom?page=2&tab=repositories"
  },
  {
    "site": "https://github.com/Ybrittoom?tab=repositories",
    "texto": "",
    "href": "https://github.com"
  },
  {
    "site": "https://github.com/Ybrittoom?tab=repositories",
    "texto": "Terms",
    "href": "https://docs.github.com/site-policy/github-terms/github-terms-of-service"
  },
  {
    "site": "https://github.com/Ybrittoom?tab=repositories",
    "texto": "Privacy",
    "href": "https://docs.github.com/site-policy/privacy-policies/github-privacy-statement"
  },
  {
    "site": "https://github.com/Ybrittoom?tab=repositories",
    "texto": "Security",
    "href": "https://github.com/security"
  },
  {
    "site": "https://github.com/Ybrittoom?tab=repositories",
    "texto": "Status",
    "href": "https://www.githubstatus.com/"
  },
  {
    "site": "https://github.com/Ybrittoom?tab=repositories",
    "texto": "Docs",
    "href": "https://docs.github.com/"
  },
  {
    "site": "https://github.com/Ybrittoom?tab=repositories",
    "texto": "Contact",
    "href": "https://support.github.com?tags=dotcom-footer"
  },
  {
    "site": "https://www.youtube.com/watch?v=5phnZexAvZM",
    "texto": "",
    "href": "/"
  },
  {
    "site": "https://www.youtube.com/watch?v=5phnZexAvZM",
    "texto": "",
    "href": "/"
  },
  {
    "site": "https://www.youtube.com/watch?v=5phnZexAvZM",
    "texto": "Sobre",
    "href": "https://www.youtube.com/about/"
  },
  {
    "site": "https://www.youtube.com/watch?v=5phnZexAvZM",
    "texto": "Imprensa",
    "href": "https://www.youtube.com/about/press/"
  },
  {
    "site": "https://www.youtube.com/watch?v=5phnZexAvZM",
    "texto": "Direitos autorais",
    "href": "https://www.youtube.com/about/copyright/"
  },
  {
    "site": "https://www.youtube.com/watch?v=5phnZexAvZM",
    "texto": "Entre em contato",
    "href": "/t/contact_us/"
  },
  {
    "site": "https://www.youtube.com/watch?v=5phnZexAvZM",
    "texto": "Criadores de conteúdo",
    "href": "https://www.youtube.com/creators/"
  },
  {
    "site": "https://www.youtube.com/watch?v=5phnZexAvZM",
    "texto": "Publicidade",
    "href": "https://www.youtube.com/ads/"
  },
  {
    "site": "https://www.youtube.com/watch?v=5phnZexAvZM",
    "texto": "Desenvolvedores",
    "href": "https://developers.google.com/youtube"
  },
  {
    "site": "https://www.youtube.com/watch?v=5phnZexAvZM",
    "texto": "Termos",
    "href": "/t/terms"
  },
  {
    "site": "https://www.youtube.com/watch?v=5phnZexAvZM",
    "texto": "Privacidade",
    "href": "/t/privacy"
  },
  {
    "site": "https://www.youtube.com/watch?v=5phnZexAvZM",
    "texto": "Política e segurança",
    "href": "https://www.youtube.com/about/policies/"
  },
  {
    "site": "https://www.youtube.com/watch?v=5phnZexAvZM",
    "texto": "Como funciona o YouTube",
    "href": "https://www.youtube.com/howyoutubeworks?utm_campaign=ytgen&utm_source=ythp&utm_medium=LeftNav&utm_content=txt&u=https%3A%2F%2Fwww.youtube.com%2Fhowyoutubeworks%3Futm_source%3Dythp%26utm_medium%3DLeftNav%26utm_campaign%3Dytgen"
  },
  {
    "site": "https://www.youtube.com/watch?v=5phnZexAvZM",
    "texto": "Testar os novos recursos",
    "href": "/new"
  },
  {
    "site": "https://web.whatsapp.com/",
    "texto": "",
    "href": "https://www.google.com/chrome/"
  },
  {
    "site": "https://web.whatsapp.com/",
    "texto": "Google Chrome",
    "href": "https://www.google.com/chrome/"
  },
  {
    "site": "https://web.whatsapp.com/",
    "texto": "",
    "href": "http://www.firefox.com/"
  },
  {
    "site": "https://web.whatsapp.com/",
    "texto": "Mozilla Firefox",
    "href": "http://www.firefox.com/"
  },
  {
    "site": "https://web.whatsapp.com/",
    "texto": "",
    "href": "https://www.microsoft.com/edge"
  },
  {
    "site": "https://web.whatsapp.com/",
    "texto": "Microsoft Edge",
    "href": "https://www.microsoft.com/edge"
  },
  {
    "site": "https://web.whatsapp.com/",
    "texto": "",
    "href": "https://www.opera.com/"
  },
  {
    "site": "https://web.whatsapp.com/",
    "texto": "Opera",
    "href": "https://www.opera.com/"
  },
  {
    "site": "https://web.whatsapp.com/",
    "texto": "",
    "href": "https://support.apple.com/downloads/#safari"
  },
  {
    "site": "https://web.whatsapp.com/",
    "texto": "Safari (macOS 11+ Only)",
    "href": "https://support.apple.com/downloads/#safari"
  }
]